{
    "total": 12,
    "rows": [
        {
            "processResult": null,
            "recordName": "王艺",
            "vehicleId": 10344780,
            "processStatus": "未处理",
            "score": 2,
            "punish": "100",
            "vTypeName": "危货",
            "recordTime": 1492564327376,
            "orgName": "北京分公司通州配送中心",
            "vioDesc": null,
            "vioId": -1345031745,
            "typeLvlName": "一般",
            "vioName": "逆行违章",
            "alarmMsg": null,
            "orgCode": "0112150F9p01",
            "driverId": 727506120,
            "userName": "王密田",
            "vioTime": 1492531200000,
            "vioAddr": "苏州街288号",
            "typeShortName": "未用清障车拖曳转向、照明、信号失效车",
            "typeId": 600689,
            "idNumber": "京G62000"
        },
        {
            "processResult": null,
            "recordName": "王艺",
            "vehicleId": 10386575,
            "processStatus": "未处理",
            "score": 6,
            "punish": "1000",
            "vTypeName": "其它",
            "recordTime": 1492564577653,
            "orgName": "办公室",
            "vioDesc": null,
            "vioId": -1345031743,
            "typeLvlName": "重度",
            "vioName": "超速行驶",
            "alarmMsg": null,
            "orgCode": "011005030200",
            "driverId": 727694020,
            "userName": "王翊璋",
            "vioTime": 1492444800000,
            "vioAddr": "朱辛庄",
            "typeShortName": "超速50%以上不足100%的",
            "typeId": 600562,
            "idNumber": "京GAG372"
        },
        {
            "processResult": null,
            "recordName": "王艺",
            "vehicleId": 10387247,
            "processStatus": "未处理",
            "score": 3,
            "punish": "200",
            "vTypeName": "其它",
            "recordTime": 1492564412061,
            "orgName": "机械公司",
            "vioDesc": null,
            "vioId": -1345031744,
            "typeLvlName": "中度",
            "vioName": "闯红灯照相",
            "alarmMsg": null,
            "orgCode": "0110050010",
            "driverId": 727593960,
            "userName": "王林权",
            "vioTime": 1492444800000,
            "vioAddr": "天通苑东三旗",
            "typeShortName": "不按交通信号灯通行",
            "typeId": 600707,
            "idNumber": "京N25690"
        },
        {
            "processResult": null,
            "recordName": "王艺",
            "vehicleId": 10382490,
            "processStatus": "未处理",
            "score": 0,
            "punish": "200",
            "vTypeName": "其它",
            "recordTime": 1491893527277,
            "orgName": "管道科技研究中心",
            "vioDesc": null,
            "vioId": -1353990975,
            "typeLvlName": "其他",
            "vioName": "超载或超员",
            "alarmMsg": null,
            "orgCode": "0112172212",
            "driverId": -1424324390,
            "userName": "王雪松",
            "vioTime": 1491840000000,
            "vioAddr": "北京东三旗村",
            "typeShortName": "驾驶证损毁期驾驶",
            "typeId": 600598,
            "idNumber": "京QX6R97"
        },
        {
            "processResult": null,
            "recordName": "王艺",
            "vehicleId": 10386984,
            "processStatus": "未处理",
            "score": 1,
            "punish": "100",
            "vTypeName": "其它",
            "recordTime": 1492563177433,
            "orgName": "机关车队",
            "vioDesc": null,
            "vioId": -1345031746,
            "typeLvlName": "轻微",
            "vioName": "无证驾驶",
            "alarmMsg": null,
            "orgCode": "011005001708",
            "driverId": 727301780,
            "userName": "王培钧",
            "vioTime": 1491753600000,
            "vioAddr": "大屯路地铁站",
            "typeShortName": "未随车携带行驶证",
            "typeId": 600666,
            "idNumber": "京KV9550"
        },
        {
            "processResult": null,
            "recordName": "王艺",
            "vehicleId": 10344649,
            "processStatus": "未处理",
            "score": 2,
            "punish": "200",
            "vTypeName": "危货",
            "recordTime": 1491894222887,
            "orgName": "北京分公司石楼配送中心",
            "vioDesc": null,
            "vioId": -1353990973,
            "typeLvlName": "一般",
            "vioName": "使用伪造驾驶证",
            "alarmMsg": null,
            "orgCode": "0112150F9r01",
            "driverId": 727125520,
            "userName": "李秀云",
            "vioTime": 1491753600000,
            "vioAddr": "朝阳区大屯路东",
            "typeShortName": "被牵引车除驾驶人外载人",
            "typeId": 600680,
            "idNumber": "京AG2899"
        },
        {
            "processResult": null,
            "recordName": "王艺",
            "vehicleId": 20845009,
            "processStatus": "未处理",
            "score": 6,
            "punish": "300",
            "vTypeName": "其它",
            "recordTime": 1491893362963,
            "orgName": "北京机关车队",
            "vioDesc": "醉酒驾驶机动车",
            "vioId": -1353990976,
            "typeLvlName": "重度",
            "vioName": "醉酒驾驶机动车",
            "alarmMsg": null,
            "orgCode": "0109a1250300",
            "driverId": -1545830868,
            "userName": "王长贵",
            "vioTime": 1491753600000,
            "vioAddr": "北京天通苑东三旗",
            "typeShortName": "饮酒后驾驶机动车",
            "typeId": 600564,
            "idNumber": "京NCN097"
        },
        {
            "processResult": null,
            "recordName": "王艺",
            "vehicleId": 10386976,
            "processStatus": "未处理",
            "score": 6,
            "punish": "300",
            "vTypeName": "其它",
            "recordTime": 1492565418644,
            "orgName": "基地管理处",
            "vioDesc": null,
            "vioId": -1345031741,
            "typeLvlName": "重度",
            "vioName": "酒后驾车",
            "alarmMsg": null,
            "orgCode": "011005000701",
            "driverId": 727301780,
            "userName": "王培钧",
            "vioTime": 1491667200000,
            "vioAddr": "三元桥",
            "typeShortName": "饮酒后驾驶机动车",
            "typeId": 600564,
            "idNumber": "京JN8700"
        },
        {
            "processResult": null,
            "recordName": "王艺",
            "vehicleId": 10386976,
            "processStatus": "未处理",
            "score": 6,
            "punish": "300",
            "vTypeName": "其它",
            "recordTime": 1492565418134,
            "orgName": "基地管理处",
            "vioDesc": null,
            "vioId": -1345031742,
            "typeLvlName": "重度",
            "vioName": "酒后驾车",
            "alarmMsg": null,
            "orgCode": "011005000701",
            "driverId": 727301780,
            "userName": "王培钧",
            "vioTime": 1491667200000,
            "vioAddr": "三元桥",
            "typeShortName": "饮酒后驾驶机动车",
            "typeId": 600564,
            "idNumber": "京JN8700"
        },
        {
            "processResult": "违章完成",
            "recordName": "钟国彬",
            "vehicleId": 10346976,
            "processStatus": "已处理",
            "score": 0,
            "punish": "200",
            "vTypeName": "危货",
            "recordTime": 1490323165937,
            "orgName": "河北分公司唐山配送中心车队",
            "vioDesc": null,
            "vioId": -1415158366,
            "typeLvlName": "其他",
            "vioName": "未挂实习标志",
            "alarmMsg": null,
            "orgCode": "0112150G1g00",
            "driverId": 727485390,
            "userName": "王学锋",
            "vioTime": 1490284800000,
            "vioAddr": "北京市朝阳区北苑路",
            "typeShortName": "实习期内未粘贴或悬挂实习标志",
            "typeId": 600654,
            "idNumber": "冀A0312V"
        },
        {
            "processResult": null,
            "recordName": "王艺",
            "vehicleId": 10344825,
            "processStatus": "未处理",
            "score": 0,
            "punish": "100",
            "vTypeName": "工程车",
            "recordTime": 1491894066428,
            "orgName": "非油品配送车队",
            "vioDesc": null,
            "vioId": -1353990974,
            "typeLvlName": "其他",
            "vioName": "无证驾驶",
            "alarmMsg": null,
            "orgCode": "0112150H0403",
            "driverId": 727490340,
            "userName": "王新平",
            "vioTime": 1488816000000,
            "vioAddr": "海淀区西二旗",
            "typeShortName": "在单位院内居民居住区内不避让行人",
            "typeId": 600642,
            "idNumber": "京ABK320"
        },
        {
            "processResult": "无",
            "recordName": "钟国彬",
            "vehicleId": 10322836,
            "processStatus": "已处理",
            "score": 1,
            "punish": "200",
            "vTypeName": "危货",
            "recordTime": 1451437837233,
            "orgName": "湖州分公司嘉湖配送中心嘉兴车队",
            "vioDesc": null,
            "vioId": 1665886330,
            "typeLvlName": "轻微",
            "vioName": "未按规定使用安全带",
            "alarmMsg": "钟国彬处理",
            "orgCode": "0112150M0001",
            "driverId": 727435620,
            "userName": "万晶晶",
            "vioTime": 1451404800000,
            "vioAddr": "杭绍配送中心",
            "typeShortName": "未按规定使用安全带",
            "typeId": 600658,
            "idNumber": "浙E18652"
        }
    ],
    "tableType": null
}